scrimba_mcp_unified/__init__.py
scrimba_mcp_unified/__main__.py
scrimba_mcp_unified/server.py
scrimba_teaching_mcp-3.0.4.dist-info/licenses/LICENSE
scrimba_teaching_mcp-3.0.4.dist-info/METADATA
scrimba_teaching_mcp-3.0.4.dist-info/WHEEL
scrimba_teaching_mcp-3.0.4.dist-info/entry_points.txt
scrimba_teaching_mcp-3.0.4.dist-info/top_level.txt
scrimba_teaching_mcp-3.0.4.dist-info/RECORD
